async_state_machine/__init__.py
async_state_machine/const.py
async_state_machine/exceptions.py
async_state_machine/shared.py
async_state_machine/state/__init__.py
async_state_machine/state/coro_wrappers.py
async_state_machine/state/stage_callbacks.py
async_state_machine/state/state.py
async_state_machine/state/state_runner.py
async_state_machine/state_machine.py
async_state_machine/states_enum.py
async_state_machine/typings.py
async_state_machine-0.0.4.dist-info/METADATA
async_state_machine-0.0.4.dist-info/WHEEL
async_state_machine-0.0.4.dist-info/RECORD
