Metadata-Version: 2.1
Name: async-state-machine
Version: 0.0.4
Summary: 
Author: konstantin-dudersky
Author-email: konstantin.dudersky@gmail.com
Requires-Python: >=3.11.0,<3.12.0
Classifier: Programming Language :: Python :: 3
Classifier: Programming Language :: Python :: 3.11
Requires-Dist: loguru (>=0.6.0,<0.7.0)
